{
  "1848_revolution_memorial_day": "1848 Giorno della memoria della rivoluzione",
  "1956_revolution_memorial_day": "Giorno della memoria della rivoluzione del 1956",
  "2_january": "2 gennaio",
  "75th_anniversary_of_the_uprising_of_june_17_1953": "75° anniversario della rivolta del 17 giugno 1953",
  "adelaide_cup_day": "Giornata dell'Adelaide Cup",
  "africa_day": "Giornata dell'Africa",
  "africa_day_heroes_day": "Giornata dell'Africa/Giornata degli Eroi",
  "agrarian_reform_day": "Giornata della riforma agraria",
  "air_force_day": "Giornata dell'Aeronautica Militare",
  "all_saints_day": "Giorno di Ognissanti",
  "all_saints_day_eve": "Vigilia di Ognissanti",
  "all_souls_day": "Giorno dei defunti",
  "all_souls_day_ponte": "Commemorazione dei defunti (Ponte)",
  "amazigh_new_year": "Amazigh Capodanno",
  "americas_day": "Festa dell'America",
  "ancestry_day": "Giornata degli antenati",
  "andean_new_year": "Capodanno andino",
  "annexation_of_the_party_of_nicoya_to_costa_rica": "Annessione del Partito di Nicoya al Costa Rica",
  "anniversary_of_the_arengo": "Anniversario dell'Arengo",
  "anniversary_of_the_battle_of_carabobo": "Anniversario della battaglia di Carabobo",
  "anniversary_of_the_election_of_pope_francis": "Anniversario dell'elezione di Papa Francesco",
  "anniversary_of_the_foundation_of_vatican_city": "Anniversario della fondazione della Città del Vaticano",
  "anniversary_of_the_passing_of_general_martin_miguel_de_guemes": "Anniversario della scomparsa del generale Martín Miguel de Güemes",
  "annunciation": "Annunciazione",
  "anti_fascist_struggle_day": "Giornata della lotta antifascista",
  "anzac_day": "Anzac Day",
  "archbishop_janani_luwum_day": "Mons. Janani Luwum Day",
  "armed_forces_day": "Giornata delle Forze Armate",
  "armenian_genocide_remembrance_day": "Giornata della memoria del genocidio armeno",
  "armistice_day": "Giorno dell'Armistizio",
  "army_abolition_day": "Giorno dell'abolizione dell'esercito",
  "army_day": "Festa dell'esercito",
  "arrival_day": "Giorno di arrivo",
  "ascension_day": "Giorno dell'Ascensione",
  "ash_wednesday": "Mercoledì delle Ceneri",
  "assumption_of_mary": "Assunzione di Maria",
  "ataturk_commemoration_youth_day": "Commemorazione di Atatürk e Giornata della Gioventù",
  "auckland_anniversary_day": "Giorno dell'anniversario di Auckland",
  "august_festivals": "Festival di agosto",
  "august_holiday": "Vacanze di agosto",
  "australia_day": "Giornata dell'Australia",
  "autonomy_day": "Festa dell'autonomia",
  "autumnal_equinox_day": "Giorno dell'equinozio d'autunno",
  "azores_day": "Giornata delle Azzorre",
  "balti_day": "Festa dei Bălţi",
  "bank_closing_day": "Giorno di chiusura della banca",
  "bastille_day": "Il giorno della Bastiglia",
  "battle_of_angamos": "Battaglia di Angamos",
  "battle_of_arica": "Battaglia di Arica",
  "battle_of_boyaca": "Battaglia di Boyacá",
  "battle_of_las_piedras": "Battaglia di Las Piedras",
  "battle_of_san_jacinto": "Battaglia di San Jacinto",
  "battle_of_the_boyne": "Battaglia del Boyne",
  "battle_of_vertieres_day": "Giornata della battaglia di Vertières",
  "beginning_of_the_independence_movement": "Inizio del Movimento per l'Indipendenza",
  "belgian_national_day": "Festa nazionale belga",
  "bengali_new_year": "Capodanno bengalese",
  "benito_juarezs_birthday": "Compleanno di Benito Juárez",
  "birth_of_the_blessed_virgin_mary": "Nascita della Beata Vergine Maria",
  "birthday_of_don_luis_munoz_rivera": "Compleanno di Don Luis Muñoz Rivera",
  "birthday_of_dr_jose_celso_barbosa": "Compleanno del Dott. José Celso Barbosa",
  "birthday_of_eugenio_maria_de_hostos": "Compleanno di Eugenio María de Hostos",
  "birthday_of_jose_de_diego": "Compleanno di José de Diego",
  "birthday_of_jose_gervasio_artigas_and_never_again_day": "Compleanno di José Gervasio Artigas e il Giorno Mai Più",
  "birthday_of_luis_munoz_marin": "Compleanno di Luis Muñoz Marín",
  "black_awareness_day": "Giornata della consapevolezza del nero",
  "bonifacio_day": "Festa di Bonifacio",
  "boqueron_battle_victory_day": "Giorno della vittoria della battaglia di Boqueron",
  "botswana_day_holiday": "Festa del Botswana",
  "boxing_day_bz": "Santo Stefano",
  "boxing_day_gh": "Santo Stefano",
  "boxing_day_hk": "Santo Stefano",
  "boxing_day_im": "Santo Stefano",
  "boxing_day_ke": "Santo Stefano",
  "boxing_day_ng": "Santo Stefano",
  "boxing_day_nz": "Santo Stefano",
  "british_columbia_day": "Giornata della Columbia Britannica",
  "buddhas_birthday": "Compleanno di Buddha",
  "canada_day": "Giornata del Canada",
  "canberra_day": "Giorno di Canberra",
  "candlemas": "Candelora",
  "canterbury_anniversary_day": "Giorno dell'anniversario di Canterbury",
  "canterbury_south_anniversary_day": "Giorno dell'anniversario di Canterbury (sud).",
  "capital_city_day": "Giornata della Capitale",
  "capitals_day": "Festa della Capitale",
  "caracas_city_foundation_day": "Giornata della fondazione della città di Caracas",
  "caricom_day": "Giornata del Caricom",
  "carnival": "Carnevale",
  "cassinga_day": "Cassinga Day",
  "castile_and_leon_day": "Giornata della Castiglia e León",
  "catholic_all_saints_day": "Giorno cattolico di Ognissanti",
  "catholic_christmas_day": "Giorno di Natale cattolico",
  "catholic_christmas_eve": "Vigilia di Natale cattolica",
  "catholic_st_stephens_day": "Giorno di Santo Stefano cattolico",
  "chaco_armistice": "Armistizio del Chaco",
  "chatham_islands_anniversary_day": "Giorno dell'anniversario delle Isole Chatham",
  "childrens_day": "Festa dei bambini",
  "chinese_arrival_day": "Giorno dell'arrivo cinese",
  "chinese_new_year": "Capodanno cinese",
  "chinese_new_year_spring_festival": "Capodanno cinese (Festival di Primavera)",
  "ching_ming_festival": "Festival Ching Ming",
  "christmas_day": "Il giorno di Natale",
  "christmas_day_orthodox": "Giorno di Natale (ortodosso)",
  "christmas_day_ponte": "Giorno di Natale (Ponte)",
  "christmas_day_roman_catholic": "Giorno di Natale (cattolico romano)",
  "christmas_eve": "Vigilia di Natale",
  "christmas_eve_orthodox": "Vigilia di Natale (ortodossa)",
  "christmas_eve_roman_catholic": "Vigilia di Natale (cattolica romana)",
  "chung_yeung_festival": "Festival di Chung Yeung",
  "chuseok": "Chuseok",
  "civic_holiday": "Festa Civica",
  "clean_monday": "Lunedì pulito",
  "colon_day": "Giornata del colon",
  "columbus_day": "Giorno di Cristoforo Colombo",
  "coming_of_age_day": "Giorno del raggiungimento della maggiore età",
  "commemoration_day": "Giorno della commemorazione",
  "commemoration_of_all_those_who_died_at_war": "Commemorazione di tutti i caduti in guerra",
  "commemoration_of_the_assault_of_the_moncada_garrison": "Commemorazione dell'Assalto al presidio Moncada",
  "commerce_day": "Giornata del commercio",
  "commonwealth_day": "Giornata del Commonwealth",
  "concord_day": "Giorno della Concordia",
  "congolese_genocide_day": "Giornata del genocidio congolese",
  "constitution_day": "Giorno della Costituzione",
  "constitution_memorial_day": "Giorno della memoria della Costituzione",
  "constitutionalist_revolution_of_1932": "Rivoluzione costituzionalista del 1932",
  "corpus_christi_co": "Corpus Domini",
  "culture_day": "Giornata della Cultura",
  "currency_change_day": "Giorno del cambio valuta",
  "cyprus_independence_day": "Giorno dell'Indipendenza di Cipro",
  "cyprus_national_day": "Festa nazionale di Cipro",
  "day_after_ascension_day": "Il giorno dopo l'Ascensione",
  "day_after_new_years_day": "Il giorno dopo Capodanno",
  "day_after_the_commemoration_of_the_assault_of_the_moncada_garrison": "Giorno dopo la commemorazione dell'assalto al presidio Moncada",
  "day_before_the_commemoration_of_the_assault_of_the_moncada_garrison": "Giorno prima della commemorazione dell'assalto alla guarnigione Moncada",
  "day_following_the_mid_autumn_festival": "Il giorno successivo alla Festa di Metà Autunno",
  "day_of_andalucia": "Giorno dell'Andalusia",
  "day_of_aragon": "Giorno dell'Aragona",
  "day_of_asturias": "Giorno delle Asturie",
  "day_of_castilla_la_mancha": "Giornata di Castiglia-La Mancia",
  "day_of_extremadura": "Giornata dell'Estremadura",
  "day_of_goodwill": "Giorno della buona volontà",
  "day_of_indigenous_resistance": "Giornata della Resistenza Indigena",
  "day_of_kings": "Giorno dei Re",
  "day_of_la_rioja": "Giornata della Rioja",
  "day_of_madrid": "Giorno di Madrid",
  "day_of_murcia": "Giorno di Murcia",
  "day_of_our_lady_of_the_seven_sorrows": "Giorno della Madonna dei Sette Dolori",
  "day_of_peace_and_reconciliation": "Giornata della pace e della riconciliazione",
  "day_of_reconciliation": "Giorno della Riconciliazione",
  "day_of_remembrance_for_truth_and_justice": "Giornata della memoria per la verità e la giustizia",
  "day_of_respect_for_cultural_diversity": "Giornata del rispetto per la diversità culturale",
  "day_of_restoration_of_independence": "Giorno della Restaurazione dell'Indipendenza",
  "day_of_restoration_of_independence_of_lithuania": "Giorno della restaurazione dell'indipendenza della Lituania",
  "day_of_svetitskhoveli_cathedra": "Giorno della cattedrale di Svetitskhoveli",
  "day_of_the_balearic_islands": "Giornata delle Isole Baleari",
  "day_of_the_canary_islands": "Giornata delle Isole Canarie",
  "day_of_the_cantabrian_institutions": "Giornata delle Istituzioni della Cantabria",
  "day_of_the_constitution_of_the_slovak_republic": "Giorno della Costituzione della Repubblica Slovacca",
  "day_of_the_convocation_of_the_constitutional_assembly_of_the_republic_of_latvia": "Giorno della convocazione dell'Assemblea costituente della Repubblica di Lettonia",
  "day_of_the_dead": "Il giorno dei morti",
  "day_of_the_establishment_of_the_general_framework_agreement_for_peace_in_bih": "Giorno della firma dell'Accordo quadro generale per la pace in Bosnia-Erzegovina",
  "day_of_the_establishment_of_the_slovak_republic": "Giorno della fondazione della Repubblica slovacca",
  "day_of_the_liberation_of_southern_africa": "Giornata della Liberazione dell'Africa Australe",
  "day_of_the_liberation_of_southern_africa_ponte": "Giornata della Liberazione dell'Africa Australe (Ponte)",
  "day_of_the_macedonian_revolutionary_struggle": "Giornata della lotta rivoluzionaria macedone",
  "day_of_the_maroons": "Giorno dei Maroon",
  "day_of_the_moldovan_national_army": "Giornata dell'Esercito Nazionale Moldavo",
  "day_of_the_proclamation_of_the_republic_of_latvia": "Giorno della proclamazione della Repubblica di Lettonia",
  "day_of_the_queen_of_peace": "Giorno della Regina della Pace",
  "day_of_the_race": "Giorno della gara",
  "day_of_the_republic": "Festa della Repubblica",
  "day_of_the_restoration_of_independence_of_the_republic_of_latvia": "Giorno del ripristino dell'indipendenza della Repubblica di Lettonia",
  "day_of_the_revolution": "Giorno della Rivoluzione",
  "day_of_the_valencian_community": "Giornata della Comunità Valenciana",
  "day_of_the_veterans_and_fallen_of_the_malvinas_war": "Giornata dei Veterani e dei Caduti della Guerra delle Malvinas",
  "day_of_uprising_against_occupation": "Giornata della rivolta contro l'occupazione",
  "day_of_valor": "Giorno del Valore",
  "day_of_veterans_of_the_armed_forces_and_law_enforcement_agencies": "Giornata dei Veterani delle Forze Armate e delle Forze dell'Ordine",
  "day_of_victory_over_fascism": "Giorno della vittoria sul fascismo",
  "deceased_ones_day": "Giorno dei defunti",
  "declaration_of_independence": "Dichiarazione di indipendenza",
  "declaration_of_independence_of_quito": "Dichiarazione di Indipendenza di Quito",
  "deepavali": "Deepavali",
  "defence_forces_day": "Giornata delle Forze di Difesa",
  "defender_of_the_fatherland_day": "Festa dei Difensori della Patria",
  "defender_of_ukraine_day": "Giornata dei difensori dell'Ucraina",
  "democracy_and_national_unity_day": "Giornata della democrazia e dell'unità nazionale",
  "democracy_day": "Giornata della democrazia",
  "dessalines_day": "Giorno di Dessalines",
  "discovery_day": "Giorno della scoperta",
  "discovery_of_puerto_rico": "Scoperta di Porto Rico",
  "dormition_of_the_theotokos": "Dormizione della Theotokos",
  "dragon_boat_festival": "Festa delle Barche Drago",
  "duartes_birthday": "Compleanno di Duarte",
  "early_may_bank_holiday": "Giorno festivo di inizio maggio",
  "easter_monday_al": "Lunedì di Pasquetta",
  "easter_monday_ba": "Lunedì di Pasquetta",
  "easter_monday_bg": "Lunedì di Pasquetta",
  "easter_monday_cy": "Lunedì di Pasquetta",
  "easter_monday_ge": "Lunedì di Pasquetta",
  "easter_monday_gr": "Lunedì di Pasquetta",
  "easter_monday_hk": "Lunedì di Pasquetta",
  "easter_monday_me": "Lunedì di Pasquetta",
  "easter_monday_mk": "Lunedì di Pasquetta",
  "easter_monday_ro": "Lunedì di Pasquetta",
  "easter_monday_rs": "Lunedì di Pasquetta",
  "easter_sunday": "Domenica di Pasqua",
  "easter_tuesday": "Martedì di Pasqua",
  "eight_hours_day": "Otto ore al giorno",
  "emancipation_day": "Giornata dell'emancipazione",
  "enthronement": "Intronizzazione",
  "epiphany_co": "Epifania",
  "epiphany_orthodox": "Epifania (ortodossa)",
  "errol_barrow_day": "Errol Barrow Giorno",
  "ethnic_pride_day": "Giornata dell'orgoglio etnico",
  "europe_day": "Festa dell'Europa",
  "evacuation_day": "Giorno dell'evacuazione",
  "family_day": "Giornata della famiglia",
  "farmers_day": "Festa degli agricoltori",
  "fathers_day": "Festa del papà",
  "feast_of_our_lady_of_bien_aparecida": "Festa di Nostra Signora di Bien Aparecida",
  "feast_of_our_lady_of_the_angels": "Festa della Madonna degli Angeli",
  "feast_of_our_lady_of_victories": "Festa della Madonna delle Vittorie",
  "feast_of_saint_agatha": "Festa di Sant'Agata",
  "feast_of_st_joseph": "Festa di San Giuseppe",
  "feast_of_st_pauls_shipwreck": "Festa del Naufragio di San Paolo",
  "feast_of_st_peter_and_st_paul": "Festa di San Pietro e San Paolo",
  "feast_of_the_divina_pastora": "Festa della Divina Pastora",
  "feast_of_the_immaculate_conception": "Festa dell'Immacolata Concezione",
  "feast_of_the_immaculate_conception_of_mary": "Festa dell'Immacolata Concezione di Maria",
  "feast_of_the_our_lady_of_mercy": "Festa della Madonna della Misericordia",
  "feast_of_the_virgin_of_candelaria": "Festa della Vergine della Candelaria",
  "federal_day_of_thanksgiving": "Giorno federale del Ringraziamento",
  "federal_fast_monday": "Lunedì di digiuno federale",
  "ferragosto_assumption": "Ferragosto (Assunzione)",
  "festival_day": "Giorno della festa",
  "festival_of_the_crosses": "Festa delle Croci",
  "first_day_of_summer": "Primo giorno d'estate",
  "flag_and_universities_day": "Giornata della Bandiera e delle Università",
  "flag_day": "Giorno della bandiera",
  "foundation_anniversary_day_of_san_cristobal_tachira": "Giorno dell'Anniversario della Fondazione di San Cristóbal, Táchira",
  "foundation_day": "Giorno della Fondazione",
  "founders_day": "Festa dei Fondatori",
  "founding_of_asuncion": "Fondazione di Asunción",
  "francisco_morazans_day_soldiers_day": "Festa di Francisco Morazán/Festa del Soldato",
  "freedom_day": "Giorno della Libertà",
  "friday_before_afl_grand_final_tentative_date": "Venerdì prima della finale dell'AFL (data provvisoria)",
  "galician_literature_day": "Giornata della Letteratura Galiziana",
  "garifuna_settlement_day": "Giorno dell'insediamento di Garifuna",
  "general_jose_de_san_martin_memorial_day": "Giorno della Memoria del Generale José de San Martín",
  "general_manuel_belgrano_memorial_day": "Giorno della Memoria del Generale Manuel Belgrano",
  "general_prayer_day": "Giornata di preghiera generale",
  "geneva_prayday": "Giornata di preghiera di Ginevra",
  "genocide_remembrance_day": "Giornata della memoria del genocidio",
  "george_price_day": "George Price Giorno",
  "german_unity_day": "Giorno dell'Unità Tedesca",
  "gibraltar_national_day": "Festa nazionale di Gibilterra",
  "gold_cup_parade_day": "Giorno della parata della Coppa d'Oro",
  "good_friday_ba": "Venerdì Santo",
  "good_friday_bg": "Venerdì Santo",
  "good_friday_cy": "Venerdì Santo",
  "good_friday_ge": "Venerdì Santo",
  "good_friday_gr": "Venerdì Santo",
  "good_friday_me": "Venerdì Santo",
  "good_friday_mk": "Venerdì Santo",
  "good_friday_ro": "Venerdì Santo",
  "good_friday_rs": "Venerdì Santo",
  "great_patriotic_war_against_fascism_victory_day": "Giorno della Vittoria della Grande Guerra Patriottica contro il Fascismo",
  "greek_independence_day": "Giorno dell'indipendenza greca",
  "green_march": "Marzo Verde",
  "green_monday": "Lunedì verde",
  "greenery_day": "Giornata del verde",
  "hangul_day": "Giorno dell'Hangul",
  "hari_raya_haji_tentative_date": "Hari Raya Haji (data provvisoria)",
  "hari_raya_puasa": "Hari Raya Puasa",
  "hawkes_bay_anniversary_day": "Giorno dell'anniversario di Hawke's Bay",
  "heritage_day": "Giornata del Patrimonio",
  "heroes_day": "Giorno degli eroi",
  "heroess_day": "Festa degli Eroi",
  "holy_saturday": "Sabato Santo",
  "holy_thursday": "Giovedì Santo",
  "hong_kong_special_administrative_region_establishment_day": "Giorno dell'istituzione della regione amministrativa speciale di Hong Kong",
  "human_rights_day": "Giornata dei diritti umani",
  "icelandic_national_day": "Festa nazionale islandese",
  "immaculate_conception": "Immacolata Concezione",
  "immaculate_conception_day": "Giorno dell'Immacolata Concezione",
  "inauguration_day": "Giorno dell'inaugurazione",
  "independence_and_national_day": "Indipendenza e Festa Nazionale",
  "independence_and_unity_day": "Giorno dell'Indipendenza e dell'Unità",
  "independence_day": "Giorno dell'Indipendenza",
  "independence_day_moldova": "Giorno dell'Indipendenza (Moldavia)",
  "independence_day_ponte": "Giorno dell'Indipendenza (Ponte)",
  "independence_movement_day": "Giornata del Movimento per l'Indipendenza",
  "independence_of_cartagena": "Indipendenza di Cartagena",
  "independence_of_cuenca": "Indipendenza di Cuenca",
  "independence_of_guayaquil": "Indipendenza di Guayaquil",
  "independent_czechoslovak_state_day": "Festa dello Stato cecoslovacco indipendente",
  "indian_arrival_day": "Giorno dell'arrivo indiano",
  "indigenous_peoples_day": "Giornata dei popoli indigeni",
  "indigenous_resistance_day": "Giornata della Resistenza Indigena",
  "integration_of_primorska_into_the_homeland": "Integrazione della Primorska nella patria",
  "international_mother_language_day": "Giornata internazionale della lingua madre",
  "international_womens_day_ponte": "Giornata internazionale della donna (Ponte)",
  "international_workers_day": "Giornata internazionale dei lavoratori",
  "international_working_day": "Giornata lavorativa internazionale",
  "islander_day": "Giornata degli isolani",
  "jamhuri_day": "Giorno dello Jamhuri",
  "jan_hus_day": "Jan Hus Day",
  "jani_day": "Giorno di Jāņi",
  "javanese_arrival_day": "Giorno dell'arrivo giavanese",
  "journalists_day": "Giornata dei giornalisti",
  "juan_santamaria_day": "Festa di Juan Santamaría",
  "july_mass_uprising_day": "Giorno della rivolta di massa di luglio",
  "june_30_revolution": "Rivoluzione del 30 giugno",
  "june_holiday": "Vacanze di giugno",
  "juneteenth_national_independence_day": "Juneteenth Giorno dell'Indipendenza Nazionale",
  "kadooment_day": "Giorno di Kadooment",
  "kazakhstan_peoples_unity_day": "Giornata dell'Unità Popolare del Kazakistan",
  "keti_koti": "Keti Koti",
  "kimbangus_day": "Giorno di Kimbangu",
  "king_letsie_iiis_birthday": "Compleanno di Re Letsie III",
  "kings_birthday": "Compleanno del Re",
  "kings_day": "Giorno del Re",
  "labour_and_agriculture_day": "Giornata del lavoro e dell'agricoltura",
  "labour_day_au": "Festa dei lavoratori",
  "labour_day_bz": "Festa dei lavoratori",
  "labour_day_ca": "Festa dei lavoratori",
  "labour_day_hk": "Festa dei lavoratori",
  "labour_day_jm": "Festa dei lavoratori",
  "labour_day_ke": "Festa dei lavoratori",
  "labour_day_kr": "Festa dei lavoratori",
  "labour_day_me": "Festa dei lavoratori",
  "labour_day_moldova": "Festa dei lavoratori (Moldavia)",
  "labour_day_ms": "Festa dei lavoratori",
  "labour_day_mx": "Festa dei lavoratori",
  "labour_day_nz": "Festa dei lavoratori",
  "labour_day_ponte": "Festa dei Lavoratori (Ponte)",
  "labour_day_pr": "Festa dei lavoratori",
  "labour_day_rs": "Festa dei lavoratori",
  "labour_day_sg": "Festa dei lavoratori",
  "labour_day_si": "Festa dei lavoratori",
  "labour_day_us": "Festa dei lavoratori",
  "labour_thanksgiving_day": "Giorno del Ringraziamento del lavoro",
  "landing_of_the_33_patriots_day": "Giorno dello sbarco dei 33 patrioti",
  "last_day_of_the_year": "Ultimo giorno dell'anno",
  "late_summer_bank_holiday": "Festività di fine estate",
  "laurent_desire_kabila_assassination": "Laurent-Désiré Kabila Assassinio",
  "liberation_day": "Festa della Liberazione",
  "liberation_day_ponte": "Festa della Liberazione (Ponte)",
  "liberation_from_fascism": "Liberazione dal fascismo",
  "ligo_day": "Giorno del Ligo",
  "limba_noastra_national_language_day": "Limba Noastra (Giornata nazionale della lingua)",
  "lincolns_birthday": "Compleanno di Lincoln",
  "local_election_day": "Giorno delle elezioni locali",
  "louis_riel_day": "Louis Riel Giorno",
  "lunar_new_year": "Capodanno lunare",
  "madaraka_day": "Giorno di Madaraka",
  "madeira_day": "Giorno di Madeira",
  "majority_rule_day": "Giorno della regola della maggioranza",
  "marine_day": "Giornata della Marina",
  "marlborough_anniversary_day": "Giorno dell'anniversario di Marlborough",
  "martin_luther_king_jr_day": "Martin Luther King, Jr. Giorno",
  "martyrs_day": "Festa dei Martiri",
  "mashujaa_day": "Giorno di Mashujaa",
  "matariki": "Matariki",
  "maundy_thursday": "Giovedì Santo",
  "may_day": "Primo Maggio",
  "may_day_bank_holiday": "Giorno festivo del Primo Maggio",
  "may_day_international_workers_day": "Primo Maggio / Giornata internazionale dei lavoratori",
  "may_revolution": "Rivoluzione di maggio",
  "mazingira_day": "Giornata della Mazingira",
  "melbourne_cup": "Coppa di Melbourne",
  "memorial_day": "Giorno della Memoria",
  "mid_autumn_festival": "Festa di metà autunno",
  "midsummer_day": "Giorno di mezza estate",
  "midsummer_eve": "Vigilia di mezza estate",
  "midsummer_evey": "Vigilia di mezza estate",
  "moshoeshoe_day": "Moshoeshoe Day",
  "mother_teresa_day": "Festa di Madre Teresa",
  "mothers_day": "Festa della mamma",
  "mountain_day": "Giornata della Montagna",
  "naadam_holiday": "Vacanze Naadam",
  "nafels_procession": "Processione di Näfels",
  "natal_day": "Giorno di Natale",
  "national_aboriginal_day": "Giornata nazionale degli aborigeni",
  "national_day": "Festa nazionale",
  "national_day_for_truth_and_reconciliation": "Giornata nazionale per la verità e la riconciliazione",
  "national_day_great_union": "Festa Nazionale/Grande Unione",
  "national_day_of_catalonia": "Giornata Nazionale della Catalogna",
  "national_day_of_indigenous_peoples": "Giornata Nazionale dei Popoli Indigeni",
  "national_day_of_spain": "Festa Nazionale della Spagna",
  "national_day_of_sweden": "Festa Nazionale della Svezia",
  "national_flag_day": "Giornata della bandiera nazionale",
  "national_foundation_day": "Giornata nazionale della Fondazione",
  "national_heroes_and_benefactors_day": "Giornata nazionale degli eroi e dei benefattori",
  "national_heroes_day": "Giornata nazionale degli eroi",
  "national_heroes_day_ponte": "Festa Nazionale degli Eroi (Ponte)",
  "national_holiday": "Festa nazionale",
  "national_independence_childrens_day": "Giornata nazionale dell'indipendenza e dei bambini",
  "national_patriots_day": "Giornata nazionale dei patrioti",
  "national_pupusa_festival": "Festival Nazionale della Pupusa",
  "national_sovereignty_day": "Giornata nazionale della sovranità",
  "national_unity_day": "Festa dell'Unità Nazionale",
  "national_womens_day": "Giornata nazionale della donna",
  "national_youth_day": "Giornata Nazionale della Gioventù",
  "nativity_of_mary": "Natività di Maria",
  "nativity_of_our_lady": "Natività della Madonna",
  "nauryz_meyramy": "Nauryz Meyramy",
  "navy_day": "Festa della Marina",
  "nelson_anniversary_day": "Giorno dell'anniversario di Nelson",
  "new_brunswick_day": "Giornata del Nuovo Brunswick",
  "new_year_holiday": "Vacanze di Capodanno",
  "new_years_day": "Capodanno",
  "new_years_day_ponte": "Capodanno (Ponte)",
  "nigerien_independence_day": "Giorno dell'indipendenza del Niger",
  "nigerien_republic_day": "Festa della Repubblica del Niger",
  "ninoy_aquino_day": "Ninoy Aquino Giorno",
  "nowruz": "Nowruz",
  "ochi_day": "Giorno dell'Ochi",
  "october_holiday": "Vacanze di ottobre",
  "october_revolution_day": "Giorno della Rivoluzione d'Ottobre",
  "ohi_day": "Giorno dell'Ohi",
  "orangemens_day": "Festa degli orangisti",
  "orthodox_christmas_eve": "Vigilia di Natale ortodossa",
  "otago_anniversary_day": "Giorno dell'anniversario di Otago",
  "our_lady_of_altagracia": "Nostra Signora di Altagracia",
  "our_lady_of_aparecida": "Nostra Signora di Aparecida",
  "our_lady_of_chiquinquira_day": "Festa della Madonna di Chiquinquirá",
  "our_lady_of_mercy": "Nostra Signora della Misericordia",
  "our_lady_of_mount_carmel": "Nostra Signora del Monte Carmelo",
  "pan_america_day": "Giornata della Panamerica",
  "pancasila_day": "Giorno della Pancasila",
  "paraguayan_independence": "Indipendenza del Paraguay",
  "parents_day": "Festa dei genitori",
  "patrice_lumumba_assassination": "Assassinio di Patrice Lumumba",
  "peace_day": "Giornata della Pace",
  "peace_day_ponte": "Giornata della Pace (Ponte)",
  "pentecost": "Pentecoste",
  "perry_christie_day": "Perry Christie Day",
  "picnic_day": "Giornata del picnic",
  "preseren_day": "Festa di Prešeren",
  "presidents_day": "Giorno dei Presidenti",
  "primoz_trubar_day": "Giornata di Primož Trubar",
  "proclamation_of_independence": "Proclamazione di indipendenza",
  "puerto_rico_constitution_day": "Giorno della Costituzione di Porto Rico",
  "queens_birthday": "Compleanno della regina",
  "reconciliation_day": "Giornata della riconciliazione",
  "reformation_day": "Giorno della Riforma",
  "remembrance_day": "Giorno della Memoria",
  "renovation_day": "Giorno della ristrutturazione",
  "repentance_and_prayer_day": "Giornata del pentimento e della preghiera",
  "repentance_day": "Giorno del pentimento",
  "republic_day": "Festa della Repubblica",
  "republic_proclamation_day": "Giorno della Proclamazione della Repubblica",
  "respect_for_the_aged_day": "Rispetto per la giornata degli anziani",
  "restoration_day": "Giorno della Restaurazione",
  "restoration_of_independence": "Ripristino dell'indipendenza",
  "reunification_day": "Giorno della riunificazione",
  "revolution_day": "Giorno della Rivoluzione",
  "revolution_day_2011_national_police_day": "Giorno della Rivoluzione 2011 / Giorno Nazionale della Polizia",
  "revolution_of_the_king_and_the_people": "Rivoluzione del Re e del Popolo",
  "rizal_day": "Giorno del Rizal",
  "robert_mugabe_national_youth_day": "Giornata nazionale della gioventù di Robert Mugabe",
  "rudolf_maister_day": "Rudolf Maister Giorno",
  "russia_day": "Festa della Russia",
  "sacred_heart": "Sacro Cuore",
  "saint_andrew_the_first_called_day": "Giorno di Sant'Andrea il Primo Chiamato",
  "saint_andrews_day": "Giorno di Sant'Andrea",
  "saint_brigids_day": "Giorno di Santa Brigida",
  "saint_clement_of_ohrid_day": "Giorno di San Clemente di Ohrid",
  "saint_devotas_day": "Festa di Santa Devota",
  "saint_florians_day": "Festa di San Floriano",
  "saint_george": "San Giorgio",
  "saint_georges_caye_day": "Giorno di Caye di San Giorgio",
  "saint_georges_day": "Giorno di San Giorgio",
  "saint_john_the_baptist": "San Giovanni Battista",
  "saint_joseph_the_worker": "San Giuseppe Lavoratore",
  "saint_josephs_day": "Festa di San Giuseppe",
  "saint_leopolds_day": "Festa di San Leopoldo",
  "saint_martins_day": "Festa di San Martino",
  "saint_marys_day": "Festa di Santa Maria",
  "saint_olavs_day": "Giorno di Sant'Olav",
  "saint_olavs_eve": "Vigilia di Sant'Olav",
  "saint_patricks_day": "Giorno di San Patrizio",
  "saint_peter_and_saint_paul": "San Pietro e San Paolo",
  "saint_ruperts_day": "Festa di San Ruperto",
  "saints_cyril_and_methodius_day": "Festa dei Santi Cirillo e Metodio",
  "santa_rosa_de_lima": "Santa Rosa de Lima",
  "santiago_apostol": "Santiago Apostolo",
  "saskatchewan_day": "Giorno del Saskatchewan",
  "second_day_of_christmas": "Secondo giorno di Natale",
  "second_day_of_lunar_new_year": "Secondo giorno del Capodanno lunare",
  "senior_race_day": "Giorno della gara senior",
  "separation_day": "Il giorno della separazione",
  "sette_giugno": "Sette Giugno",
  "shout_in_villa_de_los_santos": "Grida a Villa de los Santos",
  "showa_day": "Giorno dello Showa",
  "shrove_tuesday": "Martedì grasso",
  "simon_bolivars_birthday": "Compleanno di Simón Bolívar",
  "sinai_liberation_day": "Giorno della Liberazione del Sinai",
  "sir_seretse_khama_day": "Giorno di Sir Seretse Khama",
  "slavery_abolition_anniversary": "Anniversario dell'abolizione della schiavitù",
  "slovak_national_uprising_anniversary": "Anniversario della rivolta nazionale slovacca",
  "slovenian_sports_day": "Giornata dello sport sloveno",
  "soldiers_day": "Festa dei soldati",
  "solemnity_of_mary_mother_of_god": "Solennità di Maria, Madre di Dio",
  "south_capitals_day_cahul": "Cahul, festa della capitale del sud",
  "southland_anniversary_day": "Giorno dell'anniversario del Southland",
  "sovereigns_birthday": "Compleanno di Sovereign",
  "sovereignty_day": "Giornata della sovranità",
  "sports_day": "Giornata dello sport",
  "spring_bank_holiday": "Festività primaverili",
  "spring_day": "Giornata di Primavera",
  "st_andrews_day": "Giorno di Sant'Andrea",
  "st_berchtolds_day": "Festa di San Berchtold",
  "st_cyril_and_methodius_day": "Festa dei Santi Cirillo e Metodio",
  "st_francis_of_assisis_day": "Festa di San Francesco d'Assisi",
  "st_johns_day": "Giorno di San Giovanni",
  "st_stephens_day": "Giorno di Santo Stefano",
  "st_wenceslas_day": "Giorno di San Venceslao",
  "state_foundation_day": "Giornata della Fondazione statale",
  "statehood_day": "Giornata dello Stato",
  "struggle_for_freedom_and_democracy_day": "Giornata della lotta per la libertà e la democrazia",
  "summer_bank_holiday": "Vacanze estive",
  "summer_day": "Giorno d'estate",
  "swiss_national_day": "Festa nazionale svizzera",
  "taranaki_anniversary_day": "Giorno dell'anniversario di Taranaki",
  "teachers_day": "Festa degli insegnanti",
  "thanksgiving": "Ringraziamento",
  "thanksgiving_day": "Giorno del Ringraziamento",
  "the_battle_of_pichincha": "La battaglia di Pichincha",
  "the_day_of_restoration_of_the_state_of_lithuania": "Il Giorno della Restaurazione dello Stato della Lituania",
  "the_day_of_the_cross": "Il Giorno della Croce",
  "the_emperors_birthday": "Il compleanno dell'Imperatore",
  "the_feast_of_san_marino_and_the_republic": "La Festa di San Marino e della Repubblica",
  "the_feast_of_the_immaculate_conception": "La Festa dell'Immacolata Concezione",
  "the_immaculate_conception": "L'Immacolata Concezione",
  "third_day_of_lunar_new_year": "Terzo giorno del Capodanno lunare",
  "three_kings_day_epiphany": "Giorno dei Re Magi / Epifania",
  "tiradentes": "Tiradentes",
  "traditional_day": "Giornata tradizionale",
  "triumph_of_the_revolution": "Trionfo della Rivoluzione",
  "truman_day": "Il giorno di Truman",
  "tynwald_day": "Giornata di Tynwald",
  "ullortuneq": "Ullortuneq",
  "unification_day": "Giorno dell'Unificazione",
  "unification_of_prekmurje_slovenes_with_the_mother_nation": "Unificazione degli sloveni del Prekmurje con la Patria Madre",
  "union_day_small_union": "Festa dell'Unione/Piccola Unione",
  "unity_day": "Giorno dell'Unità",
  "vernal_equinox_day": "Giorno dell'equinozio primaverile",
  "veterans_day": "Giornata dei veterani",
  "victoria_day": "Giorno della Vittoria",
  "victory_and_commemoration_day": "Giorno della Vittoria e della Commemorazione",
  "victory_and_homeland_thanksgiving_day_and_the_day_of_croatian_defenders": "Giorno del Ringraziamento della Vittoria e della Patria e Giorno dei difensori croati",
  "victory_and_peace_day": "Giornata della Vittoria e della Pace",
  "victory_day": "Giorno della Vittoria",
  "victory_day_over_fascism": "Giorno della Vittoria sul fascismo",
  "victory_day_over_nazism_in_world_war_ii": "Giorno della vittoria sul nazismo nella seconda guerra mondiale",
  "victory_in_europe_day": "Festa della Vittoria in Europa",
  "victory_of_fidel_castro": "Vittoria di Fidel Castro",
  "virgin_of_caacupe": "Vergine di Caacupe",
  "waitangi_day": "Giorno di Waitangi",
  "wellington_anniversary_day": "Giorno dell'anniversario di Wellington",
  "western_australia_day": "Giornata dell'Australia Occidentale",
  "westland_anniversary_day": "Giorno dell'anniversario di Westland",
  "whit_monday_cy": "Lunedì di Pentecoste",
  "whit_monday_gr": "Lunedì di Pentecoste",
  "whit_monday_ro": "Lunedì di Pentecoste",
  "womens_day_ga": "Festa della donna",
  "womens_day_mz": "Festa della donna",
  "womens_day_tn": "Festa della donna",
  "workers_day": "Festa dei Lavoratori",
  "workers_memorial_day": "Giornata della Memoria dei Lavoratori",
  "world_childrens_day": "Giornata mondiale dei bambini",
  "world_cup_bank_holiday": "Giorno festivo della Coppa del Mondo",
  "world_religion_day": "Giornata mondiale della religione",
  "youth_day": "Giornata della Gioventù",
  "zikra_oued_ed_dahab": "Zikra Oued Ed-Dahab"
}
