{
  "constitution_day": {
    "intro": "Der Grundlovsdag am 5. Juni erinnert an Dänemarks erste demokratische Verfassung von 1849.",
    "history": "Am 5. Juni 1849 unterzeichnete König Frederik VII. die dänische Verfassung, beendete die absolute Monarchie und begründete Demokratie und Parlament. Am selben Datum 1953 folgte eine große Revision, darunter die weibliche Thronfolge – daher die doppelte Bedeutung.",
    "traditions": "Der Grundlovsdag ist traditionell ein Tag politischer Reden und Versammlungen in Parks und Sälen in ganz Dänemark. Viele Betriebe schließen früher oder ganz, und der Tag gilt als inoffizieller Sommerauftakt.",
    "funFacts": [
      "Es ist kein formaler Feiertag, doch die meisten Betriebe schließen.",
      "Zwei Verfassungen – 1849 und 1953 – wurden an diesem Datum unterzeichnet.",
      "Die Verfassung von 1849 beendete Dänemarks absolute Monarchie."
    ]
  }
}
